{
  "attributes_groups": [
    {
      "name": "Dados",
      "page": 1,
      "order": 1,
      "type": "character_card",
      "position": "header",
      "source_type": "fixed",
      "show_on_posts": false,
      "instructions": "",
      "character_attributes": [
        { "name": "Nome", "order": "1", "description" : "Nome do personagem", "content": "Amy" },
        { "name": "Nascimento", "order": "2", "description" : "Data de nascimento", "content": "1083" },
        { "name": "Local", "order": "3", "description" : "Local de nascimento", "content": "São Paulo" },
        { "name": "Sexo", "order": "4", "description" : "", "content": "Feminino" },
        { "name": "Clã", "order": "5", "description" : "Brujah, Gangrel, Malkaviano, Nosferatu, Toreador, Tremere", "content": "Sabá" }
      ]
    },
    {
      "name": "História",
      "page": 2,
      "order": 1,
      "type": "rich_text",
      "source_type": "open",
      "position": "column_1",
      "show_on_posts": false,
      "instructions": "",
      "character_attributes": [
        {
          "content": "Lorem ipsum dolor sit amet, consectetur adipiscing elit. In consectetur metus quis cursus semper. Morbi ac pharetra lorem. Phasellus non congue dolor. Mauris molestie malesuada porta. Cras in tempor ex, sed interdum nisi. Morbi ultrices sed diam ut porttitor. Integer et tortor erat. Nam malesuada pharetra odio sed pharetra. Morbi ullamcorper nibh mi, egestas ullamcorper ipsum cursus vitae. Phasellus blandit dolor nec quam aliquam, vel fermentum massa dignissim. Duis ut justo eu diam euismod fringilla. Proin iaculis lectus at dolor placerat blandit. Phasellus bibendum faucibus posuere. Fusce et justo vel erat mollis tempor nec in quam. Aenean non tristique orci. Suspendisse imperdiet volutpat magna, sit amet euismod est blandit a. Mauris eu velit id nibh faucibus lobortis ut ac dolor. Duis faucibus nulla metus, in lacinia felis molestie semper. Nullam ac aliquet turpis, a lacinia nulla. Suspendisse id leo a dolor consequat congue. Aliquam in orci augue. Praesent ac fringilla lectus. Ut finibus lacus ut risus tempor, sed auctor risus auctor. Phasellus iaculis metus a ligula cursus porta. Donec dignissim commodo posuere. Ut aliquam dui id nisi fringilla, ut malesuada felis ultricies. Duis sed rhoncus libero, non euismod urna. Vivamus fermentum fringilla velit id finibus. Donec et urna convallis, commodo ligula porta, euismod est. Integer a sem pulvinar, sagittis nunc ac, facilisis massa. Vivamus mi odio, iaculis eget cursus eget, posuere eget nisl. In imperdiet tempor tellus id egestas. Quisque venenatis nunc quis erat volutpat, sit amet egestas eros feugiat. Nam ante dolor, porttitor nec ante et, maximus ullamcorper tellus. Vivamus scelerisque hendrerit mi ac placerat. Proin at metus augue. Proin tristique maximus lacus, non molestie odio pretium at. Morbi nisl risus, vehicula quis arcu tincidunt, dapibus ornare justo. Nullam commodo ex sit amet leo pulvinar, in hendrerit elit auctor. Duis placerat odio quis ullamcorper vulputate. Donec sollicitudin interdum augue egestas laoreet. Morbi vel nulla ipsum. Nullam euismod pretium est, vehicula vestibulum metus. Quisque eleifend sem lacus, fringilla lacinia mauris dictum ac. Curabitur imperdiet magna ligula, ut porttitor diam ullamcorper et."
        }
      ]
    },
    {
      "name": "Físicos",
      "page": 1,
      "order": 1,
      "type": "mixed",
      "position": "column_1",
      "source_type": "fixed",
      "show_on_posts": true,
      "order_on_posts": 1,
      "points": 8,
      "character_attributes": [
        {
          "name": "Força",
          "order": 1,
          "type": "bullet",
          "points": 2,
          "total": 5
        },
        {
          "name": "Destreza",
          "order": 2,
          "type": "bullet",
          "points": 4,
          "total": 5
        },
        {
          "name": "Vigor",
          "order": 3,
          "type": "bullet",
          "points": 0,
          "total": 5
        }
      ]
    },
    {
      "name": "Sociais",
      "page": 1,
      "order": 1,
      "type": "mixed",
      "position": "column_2",
      "source_type": "fixed",
      "show_on_posts": true,
      "order_on_posts": 1,
      "points": 8,
      "character_attributes": [
        {
          "name": "Carisma",
          "order": 1,
          "type": "bullet",
          "points": 5,
          "total": 5
        },
        {
          "name": "Manipulação",
          "order": 2,
          "type": "bullet",
          "points": 5,
          "total": 5
        },
        {
          "name": "Aparência",
          "order": 3,
          "type": "bullet",
          "points": 4,
          "total": 5
        }
      ]
    },
    {
      "name": "Mentais",
      "page": 1,
      "order": 1,
      "type": "mixed",
      "position": "column_3",
      "source_type": "fixed",
      "show_on_posts": true,
      "order_on_posts": 1,
      "points": 8,
      "character_attributes": [
        {
          "name": "Percepção",
          "order": 1,
          "type": "bullet",
          "points": 1,
          "total": 5
        },
        {
          "name": "Inteligência",
          "order": 2,
          "type": "bullet",
          "points": 2,
          "total": 5
        },
        {
          "name": "Raciocínio",
          "order": 3,
          "type": "bullet",
          "points": 4,
          "total": 5
        }
      ]
    }
  ]
}
